edvinspythonlib/__init__.py
edvinspythonlib/algodata.py
edvinspythonlib/imageanalysis.py
edvinspythonlib/machinelearning.py
edvinspythonlib/mathstat.py
edvinspythonlib-0.2.0.dist-info/METADATA
edvinspythonlib-0.2.0.dist-info/WHEEL
edvinspythonlib-0.2.0.dist-info/top_level.txt
edvinspythonlib-0.2.0.dist-info/RECORD
