Metadata-Version: 2.1
Name: edvinspythonlib
Version: 0.2.0
Summary: My first Python library
Author: Me
Requires-Dist: numpy
Requires-Dist: pandas
Requires-Dist: matplotlib
Requires-Dist: scikit-learn
Requires-Dist: imageio
Requires-Dist: scikit-image
